FileStream/FileStream.py
FileStream/__init__.py
FileStream-0.0.3.dist-info/METADATA
FileStream-0.0.3.dist-info/WHEEL
FileStream-0.0.3.dist-info/top_level.txt
FileStream-0.0.3.dist-info/RECORD
