Metadata-Version: 2.1
Name: FileStream
Version: 0.0.3
Summary: Share Files On Same Network Easily
Home-page: UNKNOWN
Author: Python.Stuff
Author-email: <srinathngudi11@gmail.com>
License: UNKNOWN
Keywords: python,file,stream
Platform: UNKNOWN
Classifier: Development Status :: 1 - Planning
Classifier: Intended Audience :: Developers
Classifier: Programming Language :: Python :: 3
Classifier: Operating System :: Unix
Classifier: Operating System :: MacOS :: MacOS X
Classifier: Operating System :: Microsoft :: Windows
Requires-Dist: EasyCode
